Radar parser/TI_Parser.py
Radar parser/X4_parser.py
Radar parser/__init__.py
Radar parser/test.py
Xethru_radar/TI_Parser.py
Xethru_radar/X4_parser.py
Xethru_radar/__init__.py
Xethru_radar/data_parser.py
Xethru_radar/test.py
Xethru_radar/test_lib.py
sensor_lib/TSW_IWR.py
sensor_lib/X4_parser.py
sensor_lib/X4_record_playback.py
sensor_lib/X4_threshold.py
sensor_lib/__init__.py
sensor_lib/imu_extract.py
sensor_lib/library_gui.py
sensor_lib/lidar_extract.py
sensor_lib/test.py
sensor_lib/xyz_calc.py
sensor_library_justgo13-0.2.1.dist-info/LICENSE.txt
sensor_library_justgo13-0.2.1.dist-info/METADATA
sensor_library_justgo13-0.2.1.dist-info/WHEEL
sensor_library_justgo13-0.2.1.dist-info/top_level.txt
sensor_library_justgo13-0.2.1.dist-info/RECORD
