Metadata-Version: 2.1
Name: sensor-library-justgo13
Version: 0.2.1
Summary: Library for radar and lidar parser code
Home-page: https://github.com/Justgo13/sensor_library
Author: Jason Gao
Author-email: jgao2299@gmail.com
License: UNKNOWN
Platform: UNKNOWN
Classifier: Programming Language :: Python :: 3
Classifier: License :: OSI Approved :: MIT License
Classifier: Operating System :: OS Independent
